imagedb/__init__.py
imagedb/api.py
imagedb/config.py
imagedb/db.py
imagedb/main.py
imagedb/static/index.css
imagedb/static/index.js
imagedb/templates/index.html
imagedb/util.py
imagedb/views.py
imagedb-0.2.1.3.dist-info/LICENSE
imagedb-0.2.1.3.dist-info/WHEEL
imagedb-0.2.1.3.dist-info/METADATA
imagedb-0.2.1.3.dist-info/RECORD
